helix_data_loader/__init__.py
helix_data_loader/__main__.py
helix_data_loader/cli.py
helix_data_loader/config.json
helix_data_loader/core.py
helix_data_loader/utils/__init__.py
helix_data_loader/utils/config_loader.py
helix_data_loader/utils/transaction_meter.py
tests/__init__.py
tests/test_cli.py
tests/test_config_loader.py
tests/test_core.py
tests/test_transaction_meter.py
helix_data_loader-0.4.1.dist-info/METADATA
helix_data_loader-0.4.1.dist-info/WHEEL
helix_data_loader-0.4.1.dist-info/entry_points.txt
helix_data_loader-0.4.1.dist-info/top_level.txt
helix_data_loader-0.4.1.dist-info/RECORD
