Metadata-Version: 2.4
Name: helix-data-loader
Version: 0.4.1
Summary: Data loader for Helix platform
Home-page: https://github.com/yourusername/helix-data-loader
Author: Arnaud Lacour
Author-email: arnaudlacour@pingidentity.com
Classifier: Programming Language :: Python :: 3
Classifier: License :: OSI Approved :: MIT License
Classifier: Operating System :: OS Independent
Requires-Python: >=3.6
Requires-Dist: requests
Dynamic: author
Dynamic: author-email
Dynamic: classifier
Dynamic: description
Dynamic: description-content-type
Dynamic: home-page
Dynamic: requires-dist
Dynamic: requires-python
Dynamic: summary
